fluent_telegrinder/__init__.py
fluent_telegrinder/config.py
fluent_telegrinder/i18n.py
fluent_telegrinder/rule.py
fluent_telegrinder/sources.py
fluent_telegrinder-1.0.4.dist-info/licenses/LICENSE
fluent_telegrinder-1.0.4.dist-info/METADATA
fluent_telegrinder-1.0.4.dist-info/WHEEL
fluent_telegrinder-1.0.4.dist-info/top_level.txt
fluent_telegrinder-1.0.4.dist-info/RECORD
