Metadata-Version: 2.4
Name: fluent-telegrinder
Version: 1.0.4
Summary: Fluent i18n implementation for telegrinder
Author-email: hymn4l <amerfoe@gmail.com>
Project-URL: Homepage, https://github.com/hymn4l/fluent-telegrinder/blob/main/README.md
Project-URL: Repository, https://github.com/hymn4l/fluent-telegrinder
Keywords: telegram,bot,fluent
Classifier: Programming Language :: Python :: 3
Classifier: License :: OSI Approved :: MIT License
Classifier: Operating System :: OS Independent
Requires-Python: <4.0,>=3.13
License-File: LICENSE
Requires-Dist: fluent-runtime>=0.4.0
Provides-Extra: dev
Requires-Dist: ruff>=0.13.2; extra == "dev"
Requires-Dist: telegrinder; extra == "dev"
Dynamic: license-file
